tibis/lib/args_parser.py
tibis/lib/common.py
tibis/lib/config.py
tibis/lib/create.py
tibis/lib/delete.py
tibis/lib/first_time.py
tibis/lib/list.py
tibis/lib/lock.py
tibis/lib/logger.py
tibis/lib/static.py
tibis/lib/unlock.py
tibis/tibis.py
tibis-1.1.6.dist-info/LICENSE
tibis-1.1.6.dist-info/METADATA
tibis-1.1.6.dist-info/WHEEL
tibis-1.1.6.dist-info/entry_points.txt
tibis-1.1.6.dist-info/RECORD
