Metadata-Version: 2.3
Name: tibis
Version: 1.1.6
Summary: Tibis is a secure storage manager
Author: shoxxdj
Author-email: shoxx@shoxxdj.fr
Requires-Python: >=3.8
Classifier: Programming Language :: Python :: 3
Classifier: Programming Language :: Python :: 3.8
Classifier: Programming Language :: Python :: 3.9
Classifier: Programming Language :: Python :: 3.10
Classifier: Programming Language :: Python :: 3.11
Classifier: Programming Language :: Python :: 3.12
Classifier: Programming Language :: Python :: 3.13
Requires-Dist: PGPy (>=0.6.0,<0.7.0)
Requires-Dist: PyYAML (>=6.0.1,<7.0.0)
Requires-Dist: halo (>=0.0.31,<0.0.32)
Requires-Dist: log-symbols (>=0.0.14,<0.0.15)
Requires-Dist: pyspin (>=1.1.1,<2.0.0)
Requires-Dist: simple-chalk (>=0.1.0,<0.2.0)
Requires-Dist: standard-imghdr (>=3.13.0,<4.0.0)
Requires-Dist: termcolor (>=1.1.0,<2.0.0)
Project-URL: Homepage, https://github.com/shoxxdj/tibis
